app/__init__.py
app/routes.py
app/config/__init__.py
app/config/config.json
app/config/config_manager.py
app/controllers/__init__.py
app/controllers/address_controller.py
app/controllers/block_controller.py
app/controllers/transaction_controller.py
app/utils/__init__.py
app/utils/api_client.py
app/utils/exports.py
app/utils/formatters.py
blockExplorer/__init__.py
blockExplorer/cli.py
blockexplorer-0.1.9.dist-info/licenses/LICENSE
blockexplorer-0.1.9.dist-info/METADATA
blockexplorer-0.1.9.dist-info/WHEEL
blockexplorer-0.1.9.dist-info/entry_points.txt
blockexplorer-0.1.9.dist-info/top_level.txt
blockexplorer-0.1.9.dist-info/RECORD
