Metadata-Version: 2.4
Name: blockExplorer
Version: 0.1.9
Summary: A professional blockchain explorer web application
Home-page: https://github.com/Pymmdrza/pyExplorer
Author: Mmdrza
Author-email: pymmdrza@gmail.com
Classifier: Programming Language :: Python :: 3
Classifier: License :: OSI Approved :: MIT License
Classifier: Operating System :: OS Independent
Requires-Python: >=3.10
License-File: LICENSE
Requires-Dist: asyncio>=3.4.3
Requires-Dist: flask>=3.1.0
Requires-Dist: pandas>=2.2.3
Requires-Dist: plotly>=6.0.0
Requires-Dist: python-dotenv>=1.0.1
Requires-Dist: requests>=2.32.3
Requires-Dist: weasyprint>=64.1
Requires-Dist: websockets>=13.1
Dynamic: author
Dynamic: author-email
Dynamic: classifier
Dynamic: description
Dynamic: description-content-type
Dynamic: home-page
Dynamic: license-file
Dynamic: requires-dist
Dynamic: requires-python
Dynamic: summary
